putao/__init__.py
putao/__main__.py
putao/__version__.py
putao/cli.py
putao/core.py
putao/exceptions.py
putao/jsonclasses.py
putao/model.py
putao/utau.py
putao/utils.py
putao/resamplers/__init__.py
putao/resamplers/world.py
putao/source/__init__.py
putao/source/mid.py
putao/source/mml.py
putao/source/reg.py
putao-0.4.1.dist-info/METADATA
putao-0.4.1.dist-info/WHEEL
putao-0.4.1.dist-info/entry_points.txt
putao-0.4.1.dist-info/licenses/LICENSE
putao-0.4.1.dist-info/RECORD
