Metadata-Version: 2.3
Name: putao
Version: 0.4.1
Summary: Poor man's UTAU
Project-URL: Source code, https://github.com/ongyx/putao
Author-email: Ong Yong Xin <ongyongxin2020+github@gmail.com>
License-Expression: MIT
License-File: LICENSE
Keywords: synthesis,utau
Classifier: Topic :: Multimedia :: Sound/Audio :: Sound Synthesis
Requires-Python: >=3.10
Requires-Dist: chardet~=5.2.0
Requires-Dist: click~=8.1.7
Requires-Dist: coloredlogs~=15.0.1
Requires-Dist: mido~=1.3.0
Requires-Dist: numpy~=1.26.4
Requires-Dist: pydub~=0.25.1
Requires-Dist: pyparsing~=3.1.4
Requires-Dist: pyworld~=0.3.4
Requires-Dist: setuptools
Requires-Dist: soundfile~=0.12.1
